delicious_links
