Metadata-Version: 1.0
Name: delicious-links
Version: 0.5dev-r0
Summary: Daily links publishing from Delicious to Wordpress
Home-page: http://code.google.com/p/deliciouslinks/
Author: Maksym Kozlenko
Author-email: max@kozlenko.info
License: LGPL
Keywords: delicious wordpress
Platform: UNKNOWN
Classifier: Development Status :: 3 - Alpha
Classifier: License :: OSI Approved :: GNU Library or Lesser General Public License (LGPL)
Classifier: Topic :: Utilities
